pyqdf/__init__.py
pyqdf/container.py
pyqdf/qvf.py
pyqdf/qvs.py
pyqdf/repository.py
pyqdf-1.0.0.dist-info/COPYING
pyqdf-1.0.0.dist-info/LICENSE
pyqdf-1.0.0.dist-info/METADATA
pyqdf-1.0.0.dist-info/WHEEL
pyqdf-1.0.0.dist-info/top_level.txt
pyqdf-1.0.0.dist-info/RECORD
